python_bioinformagicks/__init__.py
python_bioinformagicks/plotting/__init__.py
python_bioinformagicks/plotting/_plot_gprofiler_results.py
python_bioinformagicks/plotting/_plot_grouped_proportions.py
python_bioinformagicks/plotting/_plot_split_embedding.py
python_bioinformagicks/tools/__init__.py
python_bioinformagicks/tools/_calc_jasmine_score.py
python_bioinformagicks/tools/_call_scSNP.py
python_bioinformagicks/tools/_do_gprofiler_analysis.py
python_bioinformagicks/tools/_scale_by_group.py
python_bioinformagicks/tools/_subset_by_coordinates.py
python_bioinformagicks/tools/_subset_by_geosketching.py
python_bioinformagicks/tools/_tf_idf_markers.py
python_bioinformagicks/utilities/__init__.py
python_bioinformagicks/utilities/_get_grouped_categories.py
python_bioinformagicks/utilities/_get_proportions.py
python_bioinformagicks/utilities/_in_ignore_list.py
python_bioinformagicks/utilities/_make_combined_categorical_column.py
python_bioinformagicks/utilities/_truncate_colormap.py
python_bioinformagicks-0.4.3.dist-info/licenses/AUTHORS.rst
python_bioinformagicks-0.4.3.dist-info/licenses/LICENSE
python_bioinformagicks-0.4.3.dist-info/METADATA
python_bioinformagicks-0.4.3.dist-info/WHEEL
python_bioinformagicks-0.4.3.dist-info/top_level.txt
python_bioinformagicks-0.4.3.dist-info/RECORD
