Metadata-Version: 2.4
Name: python_bioinformagicks
Version: 0.4.3
Summary: A collection of tools for various bioinformatics tasks.
Author-email: "Sylvia N. Michki" <sylvia.michki@gmail.com>
Maintainer-email: "Sylvia N. Michki" <sylvia.michki@gmail.com>
License-Expression: GPL-3.0-or-later
Project-URL: bugs, https://github.com/sylviamic/python_bioinformagicks/issues
Project-URL: changelog, https://github.com/sylviamic/python_bioinformagicks/blob/master/HISTORY.rst
Project-URL: homepage, https://github.com/sylviamic/python_bioinformagicks
Classifier: Programming Language :: Python
Classifier: Development Status :: 4 - Beta
License-File: LICENSE
License-File: AUTHORS.rst
Requires-Dist: scanpy
Requires-Dist: anndata
Requires-Dist: numpy
Requires-Dist: pandas
Requires-Dist: scipy
Requires-Dist: geosketch
Requires-Dist: pysam
Requires-Dist: pytest
Requires-Dist: tox
Requires-Dist: build
Requires-Dist: twine
Requires-Dist: Sphinx
Requires-Dist: sphinx-book-theme
Provides-Extra: dev
Requires-Dist: coverage; extra == "dev"
Requires-Dist: mypy; extra == "dev"
Requires-Dist: pytest; extra == "dev"
Requires-Dist: ruff; extra == "dev"
Dynamic: license-file
